Metadata-Version: 2.1
Name: Pyrics
Version: 0.0.1.1
Summary: A tool to scrape lyrics, get rhymes, generate relevant lyrics with rhymes.
Home-page: https://github.com/xiedekun/Pyrics
Author: Dekun Xie (DK)
Author-email: xiedekun@outlook.com
License: MIT
Keywords: scrape,lyrics,rhymes,generation
Platform: UNKNOWN
Classifier: Intended Audience :: Developers
Classifier: License :: OSI Approved :: MIT License
Classifier: Natural Language :: English
Classifier: Programming Language :: Python :: 3.6
Classifier: Programming Language :: Python :: 3.7
Classifier: Programming Language :: Python :: 3.8
Requires-Python: >=3.6.0
License-File: LICENSE
